croupier/__init__.py
croupier/invoker.py
croupier/py.typed
croupier_sdk-0.1.0.dist-info/licenses/LICENSE
croupier_sdk-0.1.0.dist-info/METADATA
croupier_sdk-0.1.0.dist-info/WHEEL
croupier_sdk-0.1.0.dist-info/entry_points.txt
croupier_sdk-0.1.0.dist-info/top_level.txt
croupier_sdk-0.1.0.dist-info/RECORD
