Metadata-Version: 2.4
Name: croupier-sdk
Version: 0.1.0
Summary: Croupier Python SDK for Game Function Registration and File Transfer
Home-page: https://github.com/cuihairu/croupier-sdk-python
Author: cuihairu
Author-email: cuihairu <chuihairu@gmail.com>
License: MIT
Project-URL: Homepage, https://github.com/cuihairu/croupier-sdk-python
Project-URL: Repository, https://github.com/cuihairu/croupier-sdk-python
Project-URL: Documentation, https://docs.croupier.io/sdk/python
Project-URL: Bug Tracker, https://github.com/cuihairu/croupier-sdk-python/issues
Classifier: Development Status :: 4 - Beta
Classifier: Intended Audience :: Developers
Classifier: License :: OSI Approved :: MIT License
Classifier: Operating System :: OS Independent
Classifier: Programming Language :: Python :: 3
Classifier: Programming Language :: Python :: 3.12
Classifier: Programming Language :: Python :: 3.13
Classifier: Topic :: Software Development :: Libraries :: Python Modules
Requires-Python: >=3.12
License-File: LICENSE
Requires-Dist: grpcio<2.0.0,>=1.69.0
Requires-Dist: protobuf<6.0.0,>=5.29.5
Provides-Extra: dev
Requires-Dist: pytest>=7.4.0; extra == "dev"
Requires-Dist: pytest-cov>=4.1.0; extra == "dev"
Requires-Dist: pytest-asyncio>=0.21.0; extra == "dev"
Requires-Dist: black>=23.0.0; extra == "dev"
Requires-Dist: flake8>=6.0.0; extra == "dev"
Requires-Dist: mypy>=1.5.0; extra == "dev"
Requires-Dist: types-protobuf>=5.0.0; extra == "dev"
Requires-Dist: types-grpcio>=1.0.0; extra == "dev"
Provides-Extra: monitoring
Requires-Dist: prometheus-client>=0.17.0; extra == "monitoring"
Requires-Dist: structlog>=23.0.0; extra == "monitoring"
Provides-Extra: web
Requires-Dist: uvicorn>=0.23.0; extra == "web"
Requires-Dist: gunicorn>=21.0.0; extra == "web"
Requires-Dist: fastapi>=0.100.0; extra == "web"
Dynamic: author
Dynamic: home-page
Dynamic: license-file
Dynamic: requires-python
